{"game": {"good_words": ["FIGURE", "EYE", "TRIP", "SCALE", "TUBE", "ARM"], "bad_words": ["ROULETTE", "LOCH-NESS", "MATCH", "BUFFALO"]}, "overseer": {"name": "negligent_biased_base", "neglect_words": 0, "bias_neglected_words": 0, "bias_non_neglected_words": 0, "bias_factor": 1.0, "neglect_good_words": 0}, "oversights": [{"clue_critiques": {"clue": {"clue": "Torso", "targets": ["TRIP"]}, "critiques": []}, "valid_targets": ["TRIP"], "expected_score": 5, "ground_truth_score": 5, "ground_truth_similarities": {"FIGURE": 0.2916272408471861, "EYE": 0.19952463063941855, "TRIP": 0.17142318907947748, "SCALE": 0.20362798363094978, "TUBE": 0.2711586847077704, "ARM": 0.3058554479917527, "ROULETTE": 0.1364745698459179, "LOCH-NESS": 0.15866469340902212, "MATCH": 0.17287434435642265, "BUFFALO": 0.15060652356490503}, "comparisons_performed": 9, "deciding_critique": null}], "adversarial_alpha": 0.0}