{"game": {"good_words": ["SOUND", "RACKET", "SMUGGLER", "HORN", "WASHINGTON", "GREECE"], "bad_words": ["STRING", "INDIA", "GREEN", "EUROPE"]}, "overseer": {"name": "negligent_biased_base", "neglect_words": 0, "bias_neglected_words": 0, "bias_non_neglected_words": 2, "bias_factor": 0.5, "neglect_good_words": 0}, "oversights": [{"clue_critiques": {"clue": {"clue": "Gambling", "targets": []}, "critiques": []}, "valid_targets": [], "expected_score": 3, "ground_truth_score": 3, "ground_truth_similarities": {"SOUND": 0.07271863307320726, "RACKET": 0.23492123059945222, "SMUGGLER": 0.18534806502592216, "HORN": 0.08579463871208788, "WASHINGTON": 0.118350562833984, "GREECE": 0.15412752808202268, "STRING": 0.12043146267127104, "INDIA": 0.09360427037721927, "GREEN": 0.13879400459846433, "EUROPE": 0.14705892434309845}, "comparisons_performed": 9, "deciding_critique": null}], "adversarial_alpha": 0.0}